mopidy_webhooks/__init__.py
mopidy_webhooks/ext.conf
mopidy_webhooks/frontend.py
mopidy_webhooks/utils.py
mopidy_webhooks/reporters/__init__.py
mopidy_webhooks/reporters/events.py
mopidy_webhooks/reporters/status.py
Mopidy_Webhooks-1.0.1.dist-info/LICENSE
Mopidy_Webhooks-1.0.1.dist-info/METADATA
Mopidy_Webhooks-1.0.1.dist-info/WHEEL
Mopidy_Webhooks-1.0.1.dist-info/entry_points.txt
Mopidy_Webhooks-1.0.1.dist-info/top_level.txt
Mopidy_Webhooks-1.0.1.dist-info/RECORD
