Metadata-Version: 2.1
Name: Mopidy-Webhooks
Version: 1.0.1
Summary: A simple Mopidy extension that sends webhook notifications to a remote URL.
Home-page: https://github.com/paddycarey/mopidy-webhooks
Author: Patrick Carey
Author-email: paddy@wackwack.co.uk
License: Apache License, Version 2.0
Platform: UNKNOWN
Classifier: Environment :: No Input/Output (Daemon)
Classifier: Intended Audience :: End Users/Desktop
Classifier: License :: OSI Approved :: Apache Software License
Classifier: Operating System :: OS Independent
Classifier: Programming Language :: Python :: 3
Classifier: Programming Language :: Python :: 3.8
Classifier: Programming Language :: Python :: 3.9
Classifier: Topic :: Multimedia :: Sound/Audio :: Players
Requires-Python: >=3.8
License-File: LICENSE
Requires-Dist: Mopidy (>=3.1.1)
Requires-Dist: Pykka (>=2.0.1)
Requires-Dist: setuptools
Requires-Dist: requests (>=2.22)
Provides-Extra: build
Requires-Dist: build ; extra == 'build'
Requires-Dist: twine ; extra == 'build'
Provides-Extra: dev
Requires-Dist: wheel ; extra == 'dev'
Requires-Dist: invoke ; extra == 'dev'
Requires-Dist: black ; extra == 'dev'
Requires-Dist: check-manifest ; extra == 'dev'
Requires-Dist: flake8 ; extra == 'dev'
Requires-Dist: flake8-black ; extra == 'dev'
Requires-Dist: flake8-bugbear ; extra == 'dev'
Requires-Dist: flake8-isort ; extra == 'dev'
Requires-Dist: isort ; extra == 'dev'
Requires-Dist: pep8-naming ; extra == 'dev'
Requires-Dist: pytest ; extra == 'dev'
Requires-Dist: pytest-cov ; extra == 'dev'
Requires-Dist: mypy ; extra == 'dev'
Requires-Dist: types-requests ; extra == 'dev'
Requires-Dist: types-setuptools ; extra == 'dev'
Provides-Extra: lint
Requires-Dist: black ; extra == 'lint'
Requires-Dist: check-manifest ; extra == 'lint'
Requires-Dist: flake8 ; extra == 'lint'
Requires-Dist: flake8-black ; extra == 'lint'
Requires-Dist: flake8-bugbear ; extra == 'lint'
Requires-Dist: flake8-isort ; extra == 'lint'
Requires-Dist: isort ; extra == 'lint'
Requires-Dist: pep8-naming ; extra == 'lint'
Provides-Extra: test
Requires-Dist: pytest ; extra == 'test'
Requires-Dist: pytest-cov ; extra == 'test'
Provides-Extra: typecheck
Requires-Dist: mypy ; extra == 'typecheck'
Requires-Dist: types-requests ; extra == 'typecheck'
Requires-Dist: types-setuptools ; extra == 'typecheck'
